InstagramReelDownloader/InstagramReelDownloader.py
InstagramReelDownloader/__init__.py
InstagramReelDownloader/__pycache__/InstagramReelDownloader.cpython-38.pyc
InstagramReelDownloader-1.1.dist-info/LICENSE
InstagramReelDownloader-1.1.dist-info/METADATA
InstagramReelDownloader-1.1.dist-info/WHEEL
InstagramReelDownloader-1.1.dist-info/top_level.txt
InstagramReelDownloader-1.1.dist-info/RECORD
