Metadata-Version: 2.1
Name: InstagramReelDownloader
Version: 1.1
Summary: Instagram reel downloader using Selenium WebDriver.
Author-email: Ankushtpss <ankushkumartpss@gmail.com>
Project-URL: Homepage, https://github.com/Ankushtpss/InstagramReelDownloader
Project-URL: Bug Tracker, https://github.com/Ankushtpss/InstagramReelDownloader/issues
Keywords: InstagramReelDownloader,Instagram,Reel Downloader,Instagram Reel
Classifier: Programming Language :: Python :: 3
Classifier: License :: OSI Approved :: MIT License
Classifier: Operating System :: OS Independent
Requires-Python: >=3.8
License-File: LICENSE
Requires-Dist: selenium
Requires-Dist: webdriver-manager
